iamer
