Metadata-Version: 1.1
Name: iamer
Version: 0.1.3
Summary: AWS IAM dump and load tool
Home-page: https://github.com/percolate/iamer
Author: Laurent Raufaste
Author-email: analogue@glop.org
License: GPLv3
Keywords: aws iam boto
Platform: UNKNOWN
Classifier: Development Status :: 4 - Beta
Classifier: Environment :: Console
Classifier: Intended Audience :: System Administrators
Classifier: License :: OSI Approved :: GNU General Public License v3 (GPLv3)
Classifier: Natural Language :: English
Classifier: Operating System :: POSIX
Classifier: Programming Language :: Python
Classifier: Topic :: System :: Systems Administration
